home/egon/.kill_hogs/kill_hogs.yml
kill_hogs/__init__.py
kill_hogs/kill_hogs.py
unittests/__init__.py
unittests/test_kill_hogs.py
kill_hogs-0.1.dist-info/LICENCE
kill_hogs-0.1.dist-info/METADATA
kill_hogs-0.1.dist-info/WHEEL
kill_hogs-0.1.dist-info/entry_points.txt
kill_hogs-0.1.dist-info/top_level.txt
kill_hogs-0.1.dist-info/RECORD
