Metadata-Version: 2.1
Name: kill-hogs
Version: 0.1
Summary: A script that kills processes of users generating excessive load.It is meant with HPC login nodes in mind.
Home-page: http://packages.python.org/kill_hogs
Author: Egon Rijpkema
Author-email: e.m.a.rijpkema@rug.nl
License: GPLv3
Keywords: HPC tools load memory kill
Platform: UNKNOWN
Classifier: Development Status :: 3 - Alpha
Classifier: Topic :: Utilities
Classifier: License :: OSI Approved :: GNU General Public License v3 (GPLv3)
Requires-Python: >=3.6
